topsis_yash_saxena/topsis.py
topsis_yash_saxena/topsis_yash_saxena.py
topsis_yash_saxena-1.0.4.dist-info/LICENSE
topsis_yash_saxena-1.0.4.dist-info/METADATA
topsis_yash_saxena-1.0.4.dist-info/WHEEL
topsis_yash_saxena-1.0.4.dist-info/entry_points.txt
topsis_yash_saxena-1.0.4.dist-info/top_level.txt
topsis_yash_saxena-1.0.4.dist-info/RECORD
