Metadata-Version: 2.1
Name: topsis-yash-saxena
Version: 1.0.4
Summary: A Python pip package to apply topsis approach to rank the entries in a dataset
Home-page: https://github.com/yashsaxena972/topsis
Author: Yash Saxena
Author-email: yash972saxena@gmail.com
License: MIT
Platform: UNKNOWN
Classifier: License :: OSI Approved :: MIT License
Classifier: Programming Language :: Python :: 3
Classifier: Programming Language :: Python :: 3.7
Requires-Dist: numpy
Requires-Dist: pandas
